{"stats":{"minecraft:used":{"minecraft:netherite_sword":5,"minecraft:anvil":1,"minecraft:crafting_table":1,"minecraft:grass_block":1,"minecraft:smithing_table":1,"minecraft:spruce_sapling":1,"minecraft:spruce_log":5},"minecraft:mined":{"minecraft:spruce_leaves":4,"minecraft:spruce_log":6,"minecraft:birch_leaves":1},"minecraft:picked_up":{"minecraft:stick":4,"minecraft:rotten_flesh":2,"minecraft:spruce_sapling":1,"minecraft:spruce_log":6,"minecraft:mutton":5,"minecraft:spider_eye":1,"minecraft:white_wool":4},"minecraft:custom":{"minecraft:time_since_rest":6700,"minecraft:interact_with_smithing_table":1,"minecraft:play_time":259203,"minecraft:sprint_one_cm":176595,"minecraft:deaths":7,"minecraft:damage_taken":103,"minecraft:walk_one_cm":118478,"minecraft:walk_under_water_one_cm":15341,"minecraft:interact_with_anvil":1,"minecraft:mob_kills":6,"minecraft:jump":1313,"minecraft:damage_dealt":682,"minecraft:leave_game":9,"minecraft:walk_on_water_one_cm":1904,"minecraft:time_since_death":6653,"minecraft:total_world_time":259203,"minecraft:interact_with_crafting_table":1,"minecraft:swim_one_cm":1725,"minecraft:fall_one_cm":3474,"minecraft:fly_one_cm":1967002},"minecraft:crafted":{"minecraft:crafting_table":1,"minecraft:spruce_planks":28,"minecraft:wooden_pickaxe":1},"minecraft:killed":{"minecraft:spider":1,"minecraft:zombie":3,"minecraft:squid":1,"minecraft:salmon":1}},"DataVersion":4082}